django_pam/__init__.py
django_pam/urls.py
django_pam/accounts/__init__.py
django_pam/accounts/forms.py
django_pam/accounts/urls.py
django_pam/accounts/view_mixins.py
django_pam/accounts/views.py
django_pam/auth/__init__.py
django_pam/auth/backends.py
django_pam/static/django_pam/css/auth.css
django_pam/static/django_pam/css/modal.css
django_pam/static/django_pam/js/auth.js
django_pam/static/django_pam/js/inheritance.js
django_pam/static/django_pam/js/js.cookie-2.0.4.js
django_pam/static/django_pam/js/js.cookie-2.0.4.min.js
django_pam/static/django_pam/js/modal.js
django_pam/templates/django_pam/base.html
django_pam/templates/django_pam/accounts/_login.html
django_pam/templates/django_pam/accounts/_logout.html
django_pam/templates/django_pam/accounts/login.html
django_pam/templates/django_pam/accounts/logout.html
django_pam/templates/django_pam/modals/login.html
django_pam/templates/django_pam/modals/logout.html
django_pam-2.1.2.dist-info/LICENSE.txt
django_pam-2.1.2.dist-info/METADATA
django_pam-2.1.2.dist-info/WHEEL
django_pam-2.1.2.dist-info/top_level.txt
django_pam-2.1.2.dist-info/RECORD
